packages/__init__.py
packages/main.py
packages/create_myte/__init__.py
packages/create_myte/resources/__init__.py
packages/create_myte/resources/create_project.py
packages/create_myte/resources/delete_project.py
packages/create_myte/resources/setup_project.py
packages/create_myte/templates/template-flask-restful-api-robust/.gitignore
packages/create_myte/templates/template-flask-restful-api-robust/README.md
packages/create_myte/templates/template-flask-restful-api-robust/example.envi
packages/create_myte/templates/template-flask-restful-api-robust/requirements.txt
packages/create_myte/templates/template-flask-restful-api-robust/src/config.py
packages/create_myte/templates/template-flask-restful-api-robust/src/server.py
packages/create_myte/templates/template-flask-restful-api-robust/src/models/__init__.py
packages/create_myte/templates/template-flask-restful-api-robust/src/models/abc.py
packages/create_myte/templates/template-flask-restful-api-robust/src/models/todo.py
packages/create_myte/templates/template-flask-restful-api-robust/src/models/todo_item.py
packages/create_myte/templates/template-flask-restful-api-robust/src/models/user.py
packages/create_myte/templates/template-flask-restful-api-robust/src/models/__pycache__/__init__.cpython-311.pyc
packages/create_myte/templates/template-flask-restful-api-robust/src/models/__pycache__/abc.cpython-311.pyc
packages/create_myte/templates/template-flask-restful-api-robust/src/models/__pycache__/category.cpython-311.pyc
packages/create_myte/templates/template-flask-restful-api-robust/src/models/__pycache__/classification.cpython-311.pyc
packages/create_myte/templates/template-flask-restful-api-robust/src/models/__pycache__/editor.cpython-311.pyc
packages/create_myte/templates/template-flask-restful-api-robust/src/models/__pycache__/food.cpython-311.pyc
packages/create_myte/templates/template-flask-restful-api-robust/src/models/__pycache__/food_nutrition.cpython-311.pyc
myte-1.1.0.dist-info/LICENSE
myte-1.1.0.dist-info/METADATA
myte-1.1.0.dist-info/WHEEL
myte-1.1.0.dist-info/entry_points.txt
myte-1.1.0.dist-info/top_level.txt
myte-1.1.0.dist-info/RECORD
