Metadata-Version: 2.1
Name: myte
Version: 1.1.0
Summary: Myte allows users to choose from popular web frameworks like Flask, FastAPI, and Tornado etc when initializing a new project. After entering a project name, the user selects their preferred framework which then generates the basic directory structure and boilerplate code to get started.
Author: Samuel Doghor
Author-email: Samuel Doghor <talkto@samdoghor.com>
License: MIT License
Project-URL: Homepage, https://github.com/samdoghor/myte
Project-URL: Issues, https://github.com/samdoghor/myte/issues
Project-URL: Changelog, https://github.com/samdoghor/myte/blob/main/CHANGELOG.md
Keywords: Myte,Flask,FastAPI,Tornado,Bottle,Pyramid,CherryPy,Boilerplate,Web framework,Project bootstrapping,Framework
Classifier: Programming Language :: Python :: 3
Classifier: License :: OSI Approved :: MIT License
Classifier: Operating System :: OS Independent
Classifier: Intended Audience :: Developers
Classifier: Environment :: Console
Requires-Python: >=3.8
License-File: LICENSE
Requires-Dist: typer
Requires-Dist: inquirer
Requires-Dist: rich
